<?xml version="1.0" encoding="utf-8"?>
<!DOCTYPE hibernate-mapping PUBLIC "-//Hibernate/Hibernate Mapping DTD 3.0//EN"
"http://hibernate.sourceforge.net/hibernate-mapping-3.0.dtd">
<!-- 
    Mapping file autogenerated by MyEclipse Persistence Tools
-->
<hibernate-mapping>
    <class name="com.asiainfo.aiga.userCase.bo.AigaSubSysFolder" table="AIGA_SUB_SYS_FOLDER" schema="AIGA_HZ">
        <id name="subsysId" type="java.lang.Integer">
            <column name="SUBSYS_ID" precision="20" scale="0" />
            <generator class="sequence">
		    	<param name="sequence">AIGA_FUN_FOLDER$SEQ</param>
		    </generator>
        </id>
        <property name="sysName" type="java.lang.String">
            <column name="SYS_NAME" length="2000" />
        </property>
        <property name="createTime" type="java.sql.Timestamp">
            <column name="CREATE_TIME" length="7" />
        </property>
        <property name="updateTime" type="java.sql.Timestamp">
            <column name="UPDATE_TIME" length="7" />
        </property>
        <property name="sysId" type="java.lang.Integer">
            <column name="SYS_ID" precision="20" scale="0" />
        </property>
    </class>
</hibernate-mapping>
