<?xml version="1.0" encoding="utf-8"?>
<!DOCTYPE hibernate-mapping PUBLIC "-//Hibernate/Hibernate Mapping DTD 3.0//EN"
"http://hibernate.sourceforge.net/hibernate-mapping-3.0.dtd">
<!-- 
    Mapping file autogenerated by MyEclipse Persistence Tools
-->
<hibernate-mapping>
    <class name="com.asiainfo.aiga.groupJointDebug.bo.AigaJointDebugChange" table="AIGA_JOINT_DEBUG_CHANGE" schema="AIGA_HZ">
        <id name="changeId" type="java.lang.Integer">
            <column name="CHANGE_ID" precision="22" scale="0" />
            <generator class="sequence">
		    	<param name="sequence">AIGA_JOINT_DEBUG_CHANGE$SEQ</param>
            </generator>
        </id>
        <property name="changeTag" type="java.lang.String">
            <column name="CHANGE_TAG" />
        </property>
        <property name="changeName" type="java.lang.String">
            <column name="CHANGE_NAME" />
        </property>
        <property name="changeTaskType" type="java.lang.Short">
            <column name="CHANGE_TASK_TYPE" precision="4" scale="0" />
        </property>
        <property name="changeTaskTag" type="java.lang.String">
            <column name="CHANGE_TASK_TAG" />
        </property>
        <property name="changType" type="java.lang.Short">
            <column name="CHANG_TYPE" precision="4" scale="0" />
        </property>
        <property name="createTime" type="java.sql.Timestamp">
            <column name="CREATE_TIME" length="7" />
        </property>
        <property name="creatorId" type="java.lang.Integer">
            <column name="CREATOR_ID" precision="22" scale="0" />
        </property>
        <property name="creatorName" type="java.lang.String">
            <column name="CREATOR_NAME" />
        </property>
        <property name="auditingTime" type="java.sql.Timestamp">
            <column name="AUDITING_TIME" length="7" />
        </property>
        <property name="auditingId" type="java.lang.Integer">
            <column name="AUDITING_ID" precision="22" scale="0" />
        </property>
        <property name="auditingName" type="java.lang.String">
            <column name="AUDITING_NAME" />
        </property>
        <property name="isPass" type="java.lang.Short">
            <column name="IS_PASS" precision="4" scale="0" />
        </property>
        <property name="isDelete" type="java.lang.Short">
            <column name="IS_DELETE" precision="4" scale="0" />
        </property>
        <property name="jointDebugPlanBeginTime" type="java.sql.Timestamp">
            <column name="JOINT_DEBUG_PLAN_BEGIN_TIME" length="7" />
        </property>
        <property name="jointDebugPlanEndTime" type="java.sql.Timestamp">
            <column name="JOINT_DEBUG_PLAN_END_TIME" length="7" />
        </property>
        <property name="groupReqDevEndTime" type="java.sql.Timestamp">
            <column name="GROUP_REQ_DEV_END_TIME" length="7" />
        </property>
        <property name="provincialReqDevEndTime" type="java.sql.Timestamp">
            <column name="PROVINCIAL_REQ_DEV_END_TIME" length="7" />
        </property>
        <property name="reqPlanAccomplishTime" type="java.sql.Timestamp">
            <column name="REQ_PLAN_ACCOMPLISH_TIME" length="7" />
        </property>
        <property name="taskPlanBeginCommitTime" type="java.sql.Timestamp">
            <column name="TASK_PLAN_BEGIN_COMMIT_TIME" length="7" />
        </property>
        <property name="taskPlanEndCommitTime" type="java.sql.Timestamp">
            <column name="TASK_PLAN_END_COMMIT_TIME" length="7" />
        </property>
        <property name="contentsType" type="java.lang.Short">
            <column name="CONTENTS_TYPE" precision="4" scale="0" />
        </property>
        <property name="remarks" type="java.lang.String">
            <column name="REMARKS" />
        </property>
        <property name="subTaskTag" type="java.lang.String">
            <column name="SUB_TASK_TAG" />
        </property>
        <property name="taskTag" type="java.lang.String">
            <column name="TASK_TAG" />
        </property>
        <property name="reqTag" type="java.lang.String">
            <column name="REQ_TAG" />
        </property>
    </class>
</hibernate-mapping>
